aztec_code_generator.py
aztec_code_generator-0.11.dist-info/LICENSE
aztec_code_generator-0.11.dist-info/METADATA
aztec_code_generator-0.11.dist-info/WHEEL
aztec_code_generator-0.11.dist-info/top_level.txt
aztec_code_generator-0.11.dist-info/RECORD
