Metadata-Version: 2.1
Name: aztec-code-generator
Version: 0.11
Summary: Aztec Code generator in Python
Home-page: https://github.com/dlenski/aztec_code_generator
Author: Dmitry Alimov
Author-email: dvalimov@gmail.com
Maintainer: Daniel Lenski
Maintainer-email: dlenski@gmail.com
License: MIT
Platform: UNKNOWN
License-File: LICENSE
Provides-Extra: image
Requires-Dist: pillow (<6.0,>=3.0) ; (python_version < "3.5") and extra == 'image'
Requires-Dist: pillow (<8.0,>=3.0) ; (python_version >= "3.5" and python_version < "3.6") and extra == 'image'
Requires-Dist: pillow (>=8.0) ; (python_version >= "3.6") and extra == 'image'
